ctdk/__init__.py
ctdk/types.py
ctdk/version.py
ctdk/config/__init__.py
ctdk/config/base_config.py
ctdk/config/type_converter.py
ctdk/utils/__init__.py
ctdk/utils/env.py
ctdk/utils/log.py
ctdk/utils/tools.py
ctdk-0.0.1.240616.0.dist-info/LICENSE
ctdk-0.0.1.240616.0.dist-info/METADATA
ctdk-0.0.1.240616.0.dist-info/WHEEL
ctdk-0.0.1.240616.0.dist-info/top_level.txt
ctdk-0.0.1.240616.0.dist-info/RECORD
